{
    "AX": {
        "error": 2.7198835010989976e-07,
        "error_type": "SEM",
        "filter_outliers_dict": {
            "filter_outliers": false,
            "iterations": 0,
            "std_devs": 0,
            "use_iqr_filtering": false,
            "use_standard_deviation_filtering": false
        },
        "fit": "Average",
        "fn": 10,
        "include_baseline_error": false,
        "n": 10,
        "outlier_excluded": [],
        "reviewed": true,
        "user_excluded": [],
        "value": 2.561684485868909e-07
    },
    "H1": {
        "error": 1.7181299219634078e-07,
        "error_type": "SEM",
        "filter_outliers_dict": {
            "filter_outliers": false,
            "iterations": 0,
            "std_devs": 0,
            "use_iqr_filtering": false,
            "use_standard_deviation_filtering": false
        },
        "fit": "Average",
        "fn": 10,
        "include_baseline_error": false,
        "n": 10,
        "outlier_excluded": [],
        "reviewed": true,
        "user_excluded": [],
        "value": -9.460706769459648e-06
    },
    "H2": {
        "error": 7.514743064175448e-07,
        "error_type": "SEM",
        "filter_outliers_dict": {
            "filter_outliers": false,
            "iterations": 0,
            "std_devs": 0,
            "use_iqr_filtering": false,
            "use_standard_deviation_filtering": false
        },
        "fit": "Average",
        "fn": 10,
        "include_baseline_error": false,
        "n": 10,
        "outlier_excluded": [],
        "reviewed": true,
        "user_excluded": [],
        "value": -2.9807199824816165e-06
    },
    "L1": {
        "error": 2.3145775790244026e-07,
        "error_type": "SEM",
        "filter_outliers_dict": {
            "filter_outliers": false,
            "iterations": 0,
            "std_devs": 0,
            "use_iqr_filtering": false,
            "use_standard_deviation_filtering": false
        },
        "fit": "Average",
        "fn": 10,
        "include_baseline_error": false,
        "n": 10,
        "outlier_excluded": [],
        "reviewed": true,
        "user_excluded": [],
        "value": -5.209855771681759e-07
    },
    "L2": {
        "error": 0.07187952772566945,
        "error_type": "SEM",
        "filter_outliers_dict": {
            "filter_outliers": false,
            "iterations": 0,
            "std_devs": 0,
            "use_iqr_filtering": false,
            "use_standard_deviation_filtering": false
        },
        "fit": "Average",
        "fn": 10,
        "include_baseline_error": false,
        "n": 10,
        "outlier_excluded": [],
        "reviewed": true,
        "user_excluded": [],
        "value": 0.5500000037252903
    }
}