{
    "AX": {
        "error": 2.165684817209371e-07,
        "error_type": "SEM",
        "filter_outliers_dict": {
            "filter_outliers": false,
            "iterations": 0,
            "std_devs": 0,
            "use_iqr_filtering": false,
            "use_standard_deviation_filtering": false
        },
        "fit": "Average",
        "fn": 10,
        "include_baseline_error": false,
        "n": 10,
        "outlier_excluded": [],
        "reviewed": true,
        "user_excluded": [],
        "value": 4.3593575753675396e-07
    },
    "H1": {
        "error": 3.2597891966685444e-07,
        "error_type": "SEM",
        "filter_outliers_dict": {
            "filter_outliers": false,
            "iterations": 0,
            "std_devs": 0,
            "use_iqr_filtering": false,
            "use_standard_deviation_filtering": false
        },
        "fit": "Average",
        "fn": 10,
        "include_baseline_error": false,
        "n": 10,
        "outlier_excluded": [],
        "reviewed": true,
        "user_excluded": [],
        "value": -6.942570917090052e-06
    },
    "H2": {
        "error": 6.693423912420653e-07,
        "error_type": "SEM",
        "filter_outliers_dict": {
            "filter_outliers": false,
            "iterations": 0,
            "std_devs": 0,
            "use_iqr_filtering": false,
            "use_standard_deviation_filtering": false
        },
        "fit": "Average",
        "fn": 10,
        "include_baseline_error": false,
        "n": 10,
        "outlier_excluded": [],
        "reviewed": true,
        "user_excluded": [],
        "value": -2.933812358207888e-06
    },
    "L1": {
        "error": 3.2928294302281243e-07,
        "error_type": "SEM",
        "filter_outliers_dict": {
            "filter_outliers": false,
            "iterations": 0,
            "std_devs": 0,
            "use_iqr_filtering": false,
            "use_standard_deviation_filtering": false
        },
        "fit": "Average",
        "fn": 10,
        "include_baseline_error": false,
        "n": 10,
        "outlier_excluded": [],
        "reviewed": true,
        "user_excluded": [],
        "value": -4.2889921658684216e-07
    },
    "L2": {
        "error": 0.0835995748001765,
        "error_type": "SEM",
        "filter_outliers_dict": {
            "filter_outliers": false,
            "iterations": 0,
            "std_devs": 0,
            "use_iqr_filtering": false,
            "use_standard_deviation_filtering": false
        },
        "fit": "Average",
        "fn": 10,
        "include_baseline_error": false,
        "n": 10,
        "outlier_excluded": [],
        "reviewed": true,
        "user_excluded": [],
        "value": 0.6899999991059304
    }
}