{
    "Ar36": {
        "error": 1.515295857601496,
        "error_type": "",
        "fit": "previous",
        "references": [
            {
                "exclude": false,
                "record_id": "bc-04-N-01"
            }
        ],
        "value": 165.47617900231222
    },
    "Ar37": {
        "error": 1.7098148733698754e-07,
        "error_type": "",
        "fit": "previous",
        "references": [
            {
                "exclude": false,
                "record_id": "bc-04-N-01"
            }
        ],
        "value": 2.3618080095977403e-06
    },
    "Ar38": {
        "error": 2.2334914655159606e-07,
        "error_type": "",
        "fit": "previous",
        "references": [
            {
                "exclude": false,
                "record_id": "bc-04-N-01"
            }
        ],
        "value": 1.7615328644896056e-06
    },
    "Ar39": {
        "error": 2.4564813540853595e-07,
        "error_type": "",
        "fit": "previous",
        "references": [
            {
                "exclude": false,
                "record_id": "bc-04-N-01"
            }
        ],
        "value": 1.7466017745221257e-06
    },
    "Ar40": {
        "error": 7.947187988495236e-06,
        "error_type": "",
        "fit": "previous",
        "references": [
            {
                "exclude": false,
                "record_id": "bc-04-N-01"
            }
        ],
        "value": 0.0007809475297049646
    }
}