{
    "Ar36": {
        "error": 0.9873927852362302,
        "error_type": "",
        "fit": "previous",
        "references": [
            {
                "exclude": false,
                "record_id": "ba-01-N-3858"
            }
        ],
        "value": 88.54254178733179
    },
    "Ar37": {
        "error": 2.448800374859064e-07,
        "error_type": "",
        "fit": "previous",
        "references": [
            {
                "exclude": false,
                "record_id": "ba-01-N-3858"
            }
        ],
        "value": 2.390618453439012e-06
    },
    "Ar38": {
        "error": 3.327895467445733e-07,
        "error_type": "",
        "fit": "previous",
        "references": [
            {
                "exclude": false,
                "record_id": "ba-01-N-3858"
            }
        ],
        "value": 1.305608583403541e-06
    },
    "Ar39": {
        "error": 3.708204860968163e-07,
        "error_type": "",
        "fit": "previous",
        "references": [
            {
                "exclude": false,
                "record_id": "ba-01-N-3858"
            }
        ],
        "value": 2.4181596219584508e-06
    },
    "Ar40": {
        "error": 4.272912842924571e-06,
        "error_type": "",
        "fit": "previous",
        "references": [
            {
                "exclude": false,
                "record_id": "ba-01-N-3858"
            }
        ],
        "value": 0.0004367631710481402
    }
}