{
    "Ar36": {
        "error": 6.804542952146242e-07,
        "error_type": "",
        "fit": "previous",
        "references": [
            {
                "exclude": false,
                "record_id": "ba-01-N-3753"
            }
        ],
        "value": -1.01123893578387e-06
    },
    "Ar38": {
        "error": 6.578000476513312e-07,
        "error_type": "",
        "fit": "previous",
        "references": [
            {
                "exclude": false,
                "record_id": "ba-01-N-3753"
            }
        ],
        "value": 7.442841498745831e-07
    },
    "Ar40": {
        "error": 1.1995682181473844e-05,
        "error_type": "",
        "fit": "previous",
        "references": [
            {
                "exclude": false,
                "record_id": "ba-01-N-3753"
            }
        ],
        "value": 0.00020786415379106442
    }
}