{
    "Ar36": {
        "error": 0.44659567242315784,
        "error_type": "",
        "fit": "previous",
        "references": [
            {
                "exclude": false,
                "record_id": "ba-01-N-3966"
            }
        ],
        "value": 12.637716536713057
    },
    "Ar37": {
        "error": 1.7455272619263467e-07,
        "error_type": "",
        "fit": "previous",
        "references": [
            {
                "exclude": false,
                "record_id": "ba-01-N-3966"
            }
        ],
        "value": 2.1798791682932728e-06
    },
    "Ar38": {
        "error": 2.4697583342339427e-07,
        "error_type": "",
        "fit": "previous",
        "references": [
            {
                "exclude": false,
                "record_id": "ba-01-N-3966"
            }
        ],
        "value": 1.1041303191683333e-06
    },
    "Ar39": {
        "error": 2.1750786712559917e-07,
        "error_type": "",
        "fit": "previous",
        "references": [
            {
                "exclude": false,
                "record_id": "ba-01-N-3966"
            }
        ],
        "value": 9.566691917037228e-07
    },
    "Ar40": {
        "error": 1.1896713232907825e-06,
        "error_type": "",
        "fit": "previous",
        "references": [
            {
                "exclude": false,
                "record_id": "ba-01-N-3966"
            }
        ],
        "value": 4.32988131088706e-05
    }
}