{
    "Ar36": {
        "error": 0.7055808654162103,
        "error_type": "",
        "fit": "previous",
        "references": [
            {
                "exclude": false,
                "record_id": "ba-01-N-4218"
            }
        ],
        "value": 36.28024889363149
    },
    "Ar37": {
        "error": 2.3278524995124453e-07,
        "error_type": "",
        "fit": "previous",
        "references": [
            {
                "exclude": false,
                "record_id": "ba-01-N-4218"
            }
        ],
        "value": 1.5056666860853992e-06
    },
    "Ar38": {
        "error": 2.82950414908143e-07,
        "error_type": "",
        "fit": "previous",
        "references": [
            {
                "exclude": false,
                "record_id": "ba-01-N-4218"
            }
        ],
        "value": 7.058350733841988e-07
    },
    "Ar39": {
        "error": 1.7411101102816578e-07,
        "error_type": "",
        "fit": "previous",
        "references": [
            {
                "exclude": false,
                "record_id": "ba-01-N-4218"
            }
        ],
        "value": 2.360980424526769e-07
    },
    "Ar40": {
        "error": 3.853431740892182e-06,
        "error_type": "",
        "fit": "previous",
        "references": [
            {
                "exclude": false,
                "record_id": "ba-01-N-4218"
            }
        ],
        "value": 0.0001851629482284135
    }
}