{
    "Ar36": {
        "error": 0.6337115220317378,
        "error_type": "",
        "fit": "previous",
        "references": [
            {
                "exclude": false,
                "record_id": "ba-01-N-4301"
            }
        ],
        "value": 20.485541227231266
    },
    "Ar37": {
        "error": 2.1496873223203e-07,
        "error_type": "",
        "fit": "previous",
        "references": [
            {
                "exclude": false,
                "record_id": "ba-01-N-4301"
            }
        ],
        "value": 2.349361021045183e-06
    },
    "Ar38": {
        "error": 3.2798956808760876e-07,
        "error_type": "",
        "fit": "previous",
        "references": [
            {
                "exclude": false,
                "record_id": "ba-01-N-4301"
            }
        ],
        "value": 2.593074146966596e-07
    },
    "Ar39": {
        "error": 2.4905653806428347e-07,
        "error_type": "",
        "fit": "previous",
        "references": [
            {
                "exclude": false,
                "record_id": "ba-01-N-4301"
            }
        ],
        "value": 1.1600450672736814e-06
    },
    "Ar40": {
        "error": 1.4800735975619647e-06,
        "error_type": "",
        "fit": "previous",
        "references": [
            {
                "exclude": false,
                "record_id": "ba-01-N-4301"
            }
        ],
        "value": 0.00010197592214420843
    }
}